LICENSE
README.md
setup.py
pkld/__init__.py
pkld/pkld.py
pkld/utils.py
pkld.egg-info/PKG-INFO
pkld.egg-info/SOURCES.txt
pkld.egg-info/dependency_links.txt
pkld.egg-info/requires.txt
pkld.egg-info/top_level.txt