Metadata-Version: 2.1
Name: pkld
Version: 1.2.0
Summary: Persistent caching for Python functions
Home-page: https://github.com/shobrook/pkld
Author: shobrook
Author-email: shobrookj@gmail.com
License: MIT
Requires: filelock
Requires-Python: >=3
License-File: LICENSE
Requires-Dist: filelock
